quark/__init__.py
quark/version.py
quark/onnx/__init__.py
quark/onnx/bias_correction.py
quark/onnx/calibrate.py
quark/onnx/cpu_quantizer.py
quark/onnx/equalization.py
quark/onnx/onnx_quantizer.py
quark/onnx/optimize.py
quark/onnx/qdq_quantizer.py
quark/onnx/quant_utils.py
quark/onnx/quantize.py
quark/onnx/refine.py
quark/onnx/registry.py
quark/onnx/simulate_dpu.py
quark/onnx/simulate_dpu_softmax.py
quark/onnx/smooth_quant.py
quark/onnx/finetuning/__init__.py
quark/onnx/finetuning/fast_finetune.py
quark/onnx/finetuning/onnx_evaluate.py
quark/onnx/finetuning/onnx_subgraph.py
quark/onnx/finetuning/torch_utils.py
quark/onnx/finetuning/torch_utils_test.py
quark/onnx/finetuning/create_torch/__init__.py
quark/onnx/finetuning/create_torch/create_model.py
quark/onnx/finetuning/create_torch/create_model_ops.py
quark/onnx/finetuning/create_torch/create_model_test.py
quark/onnx/finetuning/create_torch/create_model_utils.py
quark/onnx/finetuning/create_torch/quant_base_fns.py
quark/onnx/finetuning/create_torch/quant_base_ops.py
quark/onnx/finetuning/create_torch/quant_conv_ops.py
quark/onnx/finetuning/create_torch/quant_gemm_ops.py
quark/onnx/finetuning/create_torch/quant_matmul_ops.py
quark/onnx/finetuning/create_torch/quant_norm_ops.py
quark/onnx/finetuning/train_torch/__init__.py
quark/onnx/finetuning/train_torch/train_model.py
quark/onnx/finetuning/train_torch/train_model_loss.py
quark/onnx/finetuning/train_torch/train_model_param.py
quark/onnx/gptq/__init__.py
quark/onnx/gptq/gptq.py
quark/onnx/graph_transformations/__init__.py
quark/onnx/graph_transformations/model_transformer.py
quark/onnx/graph_transformations/model_transformer_test.py
quark/onnx/graph_transformations/transforms.py
quark/onnx/graph_transformations/transforms_pipeline.py
quark/onnx/mprecision/__init__.py
quark/onnx/mprecision/auto_mixprecision.py
quark/onnx/mprecision/mixed_bfp.py
quark/onnx/operators/__init__.py
quark/onnx/operators/custom_ops/__init__.py
quark_amd-0.6.0.dist-info/LICENSE
quark_amd-0.6.0.dist-info/METADATA
quark_amd-0.6.0.dist-info/WHEEL
quark_amd-0.6.0.dist-info/top_level.txt
quark_amd-0.6.0.dist-info/RECORD
